README
setup.py
compago/__init__.py
compago/application.py
compago/command.py
compago/option.py
compago/plugin.py
compago.egg-info/PKG-INFO
compago.egg-info/SOURCES.txt
compago.egg-info/dependency_links.txt
compago.egg-info/requires.txt
compago.egg-info/top_level.txt
compago/compago_config/__init__.py
compago/compago_logging/__init__.py
compago/tests/__init__.py
compago/tests/integration/__init__.py
compago/tests/unit/__init__.py
compago/tests/unit/test_application.py
compago/tests/unit/test_command.py
compago/tests/unit/test_option.py