Metadata-Version: 1.1
Name: compago
Version: 1.4
Summary: A framework for simple command-line option parsing.
Home-page: http://github.com/jmohr/compago
Author: Justin Mohr
Author-email: jmohr@bytepulse.net
License: BSD
Platform: UNKNOWN
Classifier: Development Status :: 4 - Beta
Classifier: Environment :: Console
Classifier: Intended Audience :: Developers
Classifier: License :: OSI Approved :: BSD License
Classifier: Topic :: Software Development
